{
  "rachid": {
    "status": "online",
    "last_update": "2025-05-03T23:43:45.665826",
    "ip_address": "127.0.1.1",
    "cpu_usage": "0.7%",
    "memory_free": "28781.0 MB"
  },
  "hpc2": {
    "status": "online",
    "last_update": "2025-06-06T07:45:03.174609",
    "ip_address": "192.168.1.2",
    "cpu_usage": "38.6%",
    "memory_free": "4446.9 MB"
  },
  "controller1": {
    "status": "online",
    "last_update": "2025-06-05T22:45:01.779395",
    "ip_address": "192.168.31.3",
    "cpu_usage": "1.2%",
    "memory_free": "46682.2 MB"
  },
  "compute001": {
    "status": "online",
    "last_update": "2025-06-06T06:30:02.992146",
    "ip_address": "192.168.31.11",
    "cpu_usage": "100.0%",
    "memory_free": "20819.5 MB"
  },
  "compute005": {
    "status": "online",
    "last_update": "2025-06-06T08:30:01.774303",
    "ip_address": "192.168.31.15",
    "cpu_usage": "2.2%",
    "memory_free": "23325.8 MB"
  },
  "compute006": {
    "status": "online",
    "last_update": "2025-06-06T08:45:02.741048",
    "ip_address": "192.168.31.16",
    "cpu_usage": "2.5%",
    "memory_free": "23325.9 MB"
  },
  "compute007": {
    "status": "online",
    "last_update": "2025-06-06T09:00:02.046372",
    "ip_address": "192.168.31.17",
    "cpu_usage": "1.5%",
    "memory_free": "23317.7 MB"
  }
}